flask_ckeditor/__init__.py
flask_ckeditor/fields.py
flask_ckeditor/templates/config_target.jinja
flask_ckeditor/templates/load_ckeditor.jinja
flask_ckeditor_manager-0.1.42.dist-info/WHEEL
flask_ckeditor_manager-0.1.42.dist-info/METADATA
flask_ckeditor_manager-0.1.42.dist-info/RECORD
