Metadata-Version: 2.1
Name: flask-ckeditor-manager
Version: 0.1.42
Summary: A simple interface to use CKEditor5 with Flask
License: MIT
Author: Sebastian Salinas
Author-email: seba.salinas.delrio@gmail.com
Requires-Python: >=3.8,<4.0
Classifier: License :: OSI Approved :: MIT License
Classifier: Programming Language :: Python :: 3
Classifier: Programming Language :: Python :: 3.8
Classifier: Programming Language :: Python :: 3.9
Classifier: Programming Language :: Python :: 3.10
Classifier: Programming Language :: Python :: 3.11
Requires-Dist: Flask (>=2.2.2,<3.0.0)
Project-URL: Bug Tracker, https://github.com/SebaSalinass/flask-ckeditor/issues
Project-URL: Homepage, https://github.com/SebaSalinass/flask-ckeditor
